lv/__init__.py
lv-0.0.6.dist-info/licenses/LICENSE
lv-0.0.6.dist-info/METADATA
lv-0.0.6.dist-info/WHEEL
lv-0.0.6.dist-info/top_level.txt
lv-0.0.6.dist-info/RECORD
