Metadata-Version: 2.4
Name: lv
Version: 0.0.6
Summary: Utils to slurp stuff
Home-page: https://github.com/t-c-w/lv
Author: Thor Whalen
License: apache-2.0
Platform: any
License-File: LICENSE
Dynamic: license-file
